zyro/__init__.py
zyro/cli.py
zyro/__pycache__/__init__.cpython-312.pyc
zyro/__pycache__/cli.cpython-312.pyc
zyro/core/executor.py
zyro/core/parser.py
zyro/core/router.py
zyro/core/__pycache__/executor.cpython-312.pyc
zyro/core/__pycache__/parser.cpython-312.pyc
zyro/core/__pycache__/router.cpython-312.pyc
zyro/deployers/docker/dockerizer.py
zyro/deployers/docker/__pycache__/dockerizer.cpython-312.pyc
zyro/engine/fastapi_engine.py
zyro/engine/__pycache__/fastapi_engine.cpython-312.pyc
zyro/static/__init__.py
zyro/static/image.png
zyro/static/intro.html
zyro/static/__pycache__/__init__.cpython-312.pyc
zyro-0.7.0.dist-info/licenses/LICENSE
zyro-0.7.0.dist-info/METADATA
zyro-0.7.0.dist-info/WHEEL
zyro-0.7.0.dist-info/entry_points.txt
zyro-0.7.0.dist-info/top_level.txt
zyro-0.7.0.dist-info/RECORD
