Metadata-Version: 2.4
Name: zyro
Version: 0.7.0
Summary: A zero-code backend orchestrator that turns a YAML config into a fully functional, deployable API — no code, just config.
Author-email: "M. Sanjay Uddith Raju" <uddithmachiraju@gmail.com>
License-Expression: MIT
Requires-Python: >=3.12
License-File: LICENSE
Requires-Dist: fastapi>=0.100.0
Requires-Dist: uvicorn>=0.35.0
Requires-Dist: pydantic>=2.11.7
Requires-Dist: pyyaml>=6.0.2
Requires-Dist: httpx>=0.28.1
Requires-Dist: build>=0.10.0
Requires-Dist: twine>=3.0.0
Dynamic: license-file
